cipher_cli-0.1.0.dist-info/METADATA
cipher_cli-0.1.0.dist-info/WHEEL
cipher_cli-0.1.0.dist-info/entry_points.txt
cipher_cli-0.1.0.dist-info/licenses/LICENSE
tool/__init__.py
tool/ciphers.py
tool/decrypt.py
tool/encrypt.py
tool/main.py
tool/text.py
cipher_cli-0.1.0.dist-info/RECORD
