Metadata-Version: 2.1
Name: cipher-cli
Version: 0.1.0
Author-Email: Duncan Conduit <duncanconduit@gmail.com>
License: MIT
Requires-Python: <4.0,>=3.10
Requires-Dist: typer[all]<1.0.0,>=0.1.0
Requires-Dist: rich<14.0.0,>=13.3.5
